ttx_diff/__init__.py
ttx_diff/__main__.py
ttx_diff/_version.py
ttx_diff/cli.py
ttx_diff/core.py
ttx_diff-0.2.0.dist-info/METADATA
ttx_diff-0.2.0.dist-info/WHEEL
ttx_diff-0.2.0.dist-info/entry_points.txt
ttx_diff-0.2.0.dist-info/top_level.txt
ttx_diff-0.2.0.dist-info/RECORD
