Metadata-Version: 2.4
Name: ttx-diff
Version: 0.2.0
Summary: A tool for comparing font compiler outputs (fontc vs fontmake)
Author-email: Google Fonts <fonts@google.com>
License-Expression: Apache-2.0
Project-URL: Homepage, https://github.com/googlefonts/fontc
Project-URL: Repository, https://github.com/googlefonts/fontc
Project-URL: Issues, https://github.com/googlefonts/fontc/issues
Keywords: fonts,font-compilation,fontc,fontmake,testing
Classifier: Development Status :: 4 - Beta
Classifier: Intended Audience :: Developers
Classifier: Operating System :: OS Independent
Classifier: Programming Language :: Python :: 3
Classifier: Programming Language :: Python :: 3.10
Classifier: Programming Language :: Python :: 3.11
Classifier: Programming Language :: Python :: 3.12
Classifier: Programming Language :: Python :: 3.13
Classifier: Topic :: Software Development :: Testing
Classifier: Topic :: Text Processing :: Fonts
Requires-Python: >=3.10
Requires-Dist: absl-py
Requires-Dist: fontmake[repacker]>=3.11.0
Requires-Dist: fonttools
Requires-Dist: lxml
Requires-Dist: cdifflib
Requires-Dist: glyphsLib
Requires-Dist: gftools>=0.9.74
Requires-Dist: pyyaml
Provides-Extra: test
Requires-Dist: pytest>=7.0; extra == "test"
Requires-Dist: pytest-cov; extra == "test"
Provides-Extra: dev
Requires-Dist: pytest>=7.0; extra == "dev"
Requires-Dist: pytest-cov; extra == "dev"
Requires-Dist: ruff; extra == "dev"
